{
  "contamination": 0.02,
  "methods": [
    "IF",
    "LOF",
    "PPCA_MAH",
    "HDBSCAN"
  ],
  "thresholds": {
    "IF": 0.6125389996036457,
    "LOF": 1.5401765968927732,
    "PPCA_MAH": 150.57871334016627,
    "HDBSCAN": 0.7736218835539808
  },
  "fused_threshold": 0.9703124999999999,
  "evals": {
    "IF": {
      "silhouette": 0.5823863192516808,
      "dunn": 0.02583129863296985,
      "dbi": 1.5425237991165353
    },
    "LOF": {
      "silhouette": 0.5399415705735073,
      "dunn": 0.039361543068005767,
      "dbi": 1.6957254229422591
    },
    "PPCA_MAH": {
      "silhouette": 0.6004141872645681,
      "dunn": 0.03450799603943218,
      "dbi": 0.9470982456626407
    },
    "HDBSCAN": {
      "silhouette": 0.5937339312321497,
      "dunn": 0.04431798207631188,
      "dbi": 1.1824616967484745
    },
    "FUSED": {
      "silhouette": 0.5922485622579049,
      "dunn": 0.04832673472637323,
      "dbi": 1.1343993338928533
    }
  },
  "weights": {},
  "use_pca": false,
  "use_fa": true,
  "pca_components": 13,
  "feature_columns": [
    "nb_floor",
    "nb_appart",
    "Total Electricity Consumption (kwH)",
    "lat",
    "long",
    "Area in m^2",
    "year_norm_z",
    "kwh_residual",
    "kwh_resid_abs",
    "kwh_per_m2",
    "kwh_per_appt",
    "kwh_per_floor",
    "resid_per_m2"
  ]
}