{
  "contamination": 0.04,
  "methods": [
    "IF",
    "LOF",
    "PPCA_MAH",
    "COPULA"
  ],
  "thresholds": {
    "IF": 0.5648674741022115,
    "LOF": 1.3404560313005531,
    "PPCA_MAH": 38.98118787133262,
    "COPULA": -7.670743829672509
  },
  "fused_threshold": 0.9151920341394026,
  "evals": {
    "IF": {
      "silhouette": 0.4963310804393321,
      "dunn": 0.023863314215600298,
      "dbi": 2.0433909420015812
    },
    "LOF": {
      "silhouette": 0.35968337387968086,
      "dunn": 0.025065678610450167,
      "dbi": 3.86912201493803
    },
    "PPCA_MAH": {
      "silhouette": 0.5034483948215588,
      "dunn": 0.048664369074896796,
      "dbi": 1.1525160176737035
    },
    "COPULA": {
      "silhouette": 0.4721411009535879,
      "dunn": 0.00281843292479563,
      "dbi": 2.148123777775561
    },
    "FUSED": {
      "silhouette": 0.4620031680912009,
      "dunn": 0.024508535055230558,
      "dbi": 2.332180002215552
    }
  },
  "weights": {},
  "use_pca": false,
  "use_fa": true,
  "pca_components": 13,
  "feature_columns": [
    "nb_floor",
    "nb_appart",
    "Total Electricity Consumption (kwH)",
    "lat",
    "long",
    "Area in m^2",
    "year_norm_z",
    "kwh_residual",
    "kwh_resid_abs",
    "kwh_per_m2",
    "kwh_per_appt",
    "kwh_per_floor",
    "resid_per_m2"
  ]
}